sanic_restful_api/__init__.py
sanic_restful_api/__version__.py
sanic_restful_api/fields.py
sanic_restful_api/inputs.py
sanic_restful_api/reqparse.py
sanic_restful_api/representations/__init__.py
sanic_restful_api/representations/json.py
sanic_restful_api/utils/__init__.py
sanic_restful_api/utils/accept_mimetypes.py
sanic_restful_api/utils/crypto.py
sanic_restful_api-0.2.1.dist-info/LICENSE
sanic_restful_api-0.2.1.dist-info/METADATA
sanic_restful_api-0.2.1.dist-info/WHEEL
sanic_restful_api-0.2.1.dist-info/top_level.txt
sanic_restful_api-0.2.1.dist-info/RECORD
