Metadata-Version: 2.1
Name: sanic-restful-api
Version: 0.2.1
Summary: Simple framework for creating REST APIs
Home-page: https://github.com/linzhiming0826/sanic-restful
Author: TuoX
Author-email: 120549827@qq.com
License: MIT
Platform: any
Classifier: Programming Language :: Python :: 3.6
Classifier: Programming Language :: Python :: 3.7
Classifier: License :: OSI Approved :: MIT License
License-File: LICENSE
Requires-Dist: aniso8601 (>=0.82)
Requires-Dist: sanic (>=22.12.0)
Requires-Dist: six (>=1.3.0)
Requires-Dist: orjson (>=3.8.11)
Requires-Dist: pytz
Requires-Dist: werkzeug
